<xml xmlns="https://developers.google.com/blockly/xml">
  <variables>
    <variable id="Sk=)C%r}uS^6M}fR]Hxt">moduleTest</variable>
  </variables>
  <block type="hh_ORCHESTRATION" id="M)ZKyxG8S)|LJFqE+^ty" x="173" y="110">
    <statement name="MODULES">
      <block type="hh_module" id="Dx/hJ0tvVT6VGR,?R1uu">
        <value name="NAME">
          <block type="variables_get" id="(,10DE-q/LhnUv?)Xr1$">
            <field name="VAR" id="Sk=)C%r}uS^6M}fR]Hxt">moduleTest</field>
          </block>
        </value>
        <statement name="BODY">
          <block type="hh_print_serveur" id="(%SX%uIWmA6-dRXSzPtn">
            <value name="TEXT">
              <block type="text" id="Q{$^~*e?vd#E8u+nJ%h`">
                <field name="TEXT">module de test</field>
              </block>
            </value>
          </block>
        </statement>
      </block>
    </statement>
    <statement name="BODY">
      <block type="hh_run" id=":qa:^Pt7;RtU|N;~u`S:">
        <value name="MODULE">
          <block type="variables_get" id="Z5rfx9PYOy@D%-$Ww+%r">
            <field name="VAR" id="Sk=)C%r}uS^6M}fR]Hxt">moduleTest</field>
          </block>
        </value>
      </block>
    </statement>
  </block>
</xml>